setup.py
redpill/__init__.py
redpill/main.py
redpill/version.py
redpill.egg-info/PKG-INFO
redpill.egg-info/SOURCES.txt
redpill.egg-info/dependency_links.txt
redpill.egg-info/entry_points.txt
redpill.egg-info/requires.txt
redpill.egg-info/top_level.txt
redpill.egg-info/zip-safe