Metadata-Version: 1.0
Name: redpill
Version: 0.9
Summary: A cross-plaform package management framework
Home-page: https://github.com/tav/redpill
Author: tav
Author-email: tav@espians.com
License: Public Domain
Keywords: package management,dependency management
Platform: UNKNOWN
Classifier: Development Status :: 5 - Production/Stable
Classifier: Intended Audience :: Developers
Classifier: License :: Public Domain
Classifier: Operating System :: OS Independent
Classifier: Programming Language :: Python
